{
  "node": {
    "0a52e08c9308ca5bec9997d1cf49638a56094860": {
      "workers": {
        "app/page": "(action-browser)/./node_modules/next/dist/build/webpack/loaders/next-flight-action-entry-loader.js?actions=%5B%5B%22C%3A%5C%5CUsers%5C%5Cyu%5C%5CDesktop%5C%5Cjugg-tool-box%5C%5Capp%5C%5Clib%5C%5Cactions.ts%22%2C%5B%22signIn%22%2C%22signOut%22%2C%22regist%22%5D%5D%2C%5B%22C%3A%5C%5CUsers%5C%5Cyu%5C%5CDesktop%5C%5Cjugg-tool-box%5C%5Capp%5C%5Clib%5C%5Ccaptcha.ts%22%2C%5B%22validPuzzle%22%2C%22getPuzzle%22%5D%5D%5D&__client_imported__=true!"
      },
      "layer": {
        "app/page": "action-browser"
      }
    },
    "2cc4209a9adeaaa8b03b7b74afaa4c581be5f301": {
      "workers": {
        "app/page": "(action-browser)/./node_modules/next/dist/build/webpack/loaders/next-flight-action-entry-loader.js?actions=%5B%5B%22C%3A%5C%5CUsers%5C%5Cyu%5C%5CDesktop%5C%5Cjugg-tool-box%5C%5Capp%5C%5Clib%5C%5Cactions.ts%22%2C%5B%22signIn%22%2C%22signOut%22%2C%22regist%22%5D%5D%2C%5B%22C%3A%5C%5CUsers%5C%5Cyu%5C%5CDesktop%5C%5Cjugg-tool-box%5C%5Capp%5C%5Clib%5C%5Ccaptcha.ts%22%2C%5B%22validPuzzle%22%2C%22getPuzzle%22%5D%5D%5D&__client_imported__=true!"
      },
      "layer": {
        "app/page": "action-browser"
      }
    },
    "ebd8440c349f4772588d1515641533627a828249": {
      "workers": {
        "app/page": "(action-browser)/./node_modules/next/dist/build/webpack/loaders/next-flight-action-entry-loader.js?actions=%5B%5B%22C%3A%5C%5CUsers%5C%5Cyu%5C%5CDesktop%5C%5Cjugg-tool-box%5C%5Capp%5C%5Clib%5C%5Cactions.ts%22%2C%5B%22signIn%22%2C%22signOut%22%2C%22regist%22%5D%5D%2C%5B%22C%3A%5C%5CUsers%5C%5Cyu%5C%5CDesktop%5C%5Cjugg-tool-box%5C%5Capp%5C%5Clib%5C%5Ccaptcha.ts%22%2C%5B%22validPuzzle%22%2C%22getPuzzle%22%5D%5D%5D&__client_imported__=true!"
      },
      "layer": {
        "app/page": "action-browser"
      }
    },
    "1c3731a774d6fb952cd335caa2138ca24662237c": {
      "workers": {
        "app/page": "(action-browser)/./node_modules/next/dist/build/webpack/loaders/next-flight-action-entry-loader.js?actions=%5B%5B%22C%3A%5C%5CUsers%5C%5Cyu%5C%5CDesktop%5C%5Cjugg-tool-box%5C%5Capp%5C%5Clib%5C%5Cactions.ts%22%2C%5B%22signIn%22%2C%22signOut%22%2C%22regist%22%5D%5D%2C%5B%22C%3A%5C%5CUsers%5C%5Cyu%5C%5CDesktop%5C%5Cjugg-tool-box%5C%5Capp%5C%5Clib%5C%5Ccaptcha.ts%22%2C%5B%22validPuzzle%22%2C%22getPuzzle%22%5D%5D%5D&__client_imported__=true!"
      },
      "layer": {
        "app/page": "action-browser"
      }
    },
    "1b72865bcefe21f04593d018adf30b170cc87487": {
      "workers": {
        "app/page": "(action-browser)/./node_modules/next/dist/build/webpack/loaders/next-flight-action-entry-loader.js?actions=%5B%5B%22C%3A%5C%5CUsers%5C%5Cyu%5C%5CDesktop%5C%5Cjugg-tool-box%5C%5Capp%5C%5Clib%5C%5Cactions.ts%22%2C%5B%22signIn%22%2C%22signOut%22%2C%22regist%22%5D%5D%2C%5B%22C%3A%5C%5CUsers%5C%5Cyu%5C%5CDesktop%5C%5Cjugg-tool-box%5C%5Capp%5C%5Clib%5C%5Ccaptcha.ts%22%2C%5B%22validPuzzle%22%2C%22getPuzzle%22%5D%5D%5D&__client_imported__=true!"
      },
      "layer": {
        "app/page": "action-browser"
      }
    }
  },
  "edge": {},
  "encryptionKey": "1nUWrL1XNAaZQrXxLf04MW6psvt+kLgDAT76wDRJ6e4="
}